filddle/__init__.py
filddle/filddle.py
filddle-0.1.dist-info/METADATA
filddle-0.1.dist-info/WHEEL
filddle-0.1.dist-info/top_level.txt
filddle-0.1.dist-info/RECORD
