Metadata-Version: 2.1
Name: filddle
Version: 0.1
Summary: light-weight file classifier
Home-page: https://github.com/khaingmyelkhant/Filddle
Author: Khaing Myae Khant
Author-email: kaelkhantweb@gmail.com
License: UNKNOWN
Platform: UNKNOWN
Classifier: Programming Language :: Python :: 3
Classifier: License :: OSI Approved :: GNU General Public License v3 (GPLv3)
Classifier: Operating System :: OS Independent
Requires-Python: >=3.6
